{
  "deal_id": "ie-ye-2026",
  "deal_version": 1,
  "home_country": {
    "id": "6813b6d446e731854c7ac7fe",
    "code": "IE",
    "name": "Ireland"
  },
  "host_country": {
    "code": "YE",
    "name": "Yemen",
    "id": "683ddd2c24b5a2e114af160f"
  },
  "home_citizen_rebate": 0.25,
  "non_home_citizen_rebate": 0.375,
  "current_week": {
    "week_start": "2026-06-29",
    "days": [
      {
        "date": "2026-07-05",
        "row": {
          "factories": 22,
          "workers": 31,
          "home_workers": 11,
          "partner_workers": 20,
          "wages": 1279.46,
          "gross_tax": 51.18,
          "home_worker_tax": 28.33,
          "partner_worker_tax": 22.84,
          "manual_rebate_due": 15.65,
          "auto_remit_tax": 15.35,
          "host_retained": 20.17
        }
      }
    ],
    "totals": {
      "factories": 22,
      "workers": 31,
      "home_workers": 11,
      "partner_workers": 20,
      "wages": 1279.46,
      "gross_tax": 51.18,
      "home_worker_tax": 28.33,
      "partner_worker_tax": 22.84,
      "manual_rebate_due": 15.65,
      "auto_remit_tax": 15.35,
      "host_retained": 20.17
    }
  },
  "previous_week": null,
  "updated_at": "2026-07-05T14:11:11.811690+00:00"
}