{
  "week_start": "2026-07-20",
  "days": [
    {
      "date": "2026-07-20",
      "countries": [
        {
          "id": "683ddd2c24b5a2e114af160f",
          "name": "Yemen",
          "code": "ye",
          "rate": 5.0,
          "factories": 46,
          "workers": 73,
          "irish_workers": 23,
          "foreign_workers": 50,
          "wages": 2702.39,
          "tax": 135.12,
          "irish_worker_tax": 54.13,
          "foreign_worker_tax": 80.98,
          "manual_rebate_due": 43.9,
          "host_retained": 50.68,
          "irish_rebate": 0.25,
          "foreign_rebate": 0.375,
          "deal_version": 1
        },
        {
          "id": "6813b6d446e731854c7ac7ba",
          "name": "Serbia",
          "code": "rs",
          "rate": 10.0,
          "factories": 23,
          "workers": 23,
          "irish_workers": 7,
          "foreign_workers": 16,
          "wages": 950.13,
          "tax": 95.01,
          "irish_worker_tax": 25.81,
          "foreign_worker_tax": 69.21,
          "manual_rebate_due": 0.0,
          "host_retained": 66.51,
          "irish_rebate": 0,
          "foreign_rebate": 0,
          "deal_version": 1
        },
        {
          "id": "6813b6d546e731854c7ac862",
          "name": "India",
          "code": "in",
          "rate": 4.0,
          "factories": 14,
          "workers": 17,
          "irish_workers": 8,
          "foreign_workers": 9,
          "wages": 994.89,
          "tax": 39.8,
          "irish_worker_tax": 18.53,
          "foreign_worker_tax": 21.27,
          "manual_rebate_due": 0.0,
          "host_retained": 27.86,
          "irish_rebate": 0,
          "foreign_rebate": 0,
          "deal_version": 1
        },
        {
          "id": "6873d0ea1758b40e712b5f16",
          "name": "Djibouti",
          "code": "dj",
          "rate": 7.5,
          "factories": 13,
          "workers": 15,
          "irish_workers": 5,
          "foreign_workers": 10,
          "wages": 450.56,
          "tax": 33.79,
          "irish_worker_tax": 25.28,
          "foreign_worker_tax": 8.51,
          "manual_rebate_due": 0.0,
          "host_retained": 23.65,
          "irish_rebate": 0,
          "foreign_rebate": 0,
          "deal_version": 1
        },
        {
          "id": "683ddd2c24b5a2e114af15f7",
          "name": "Namibia",
          "code": "na",
          "rate": 6.9,
          "factories": 8,
          "workers": 8,
          "irish_workers": 2,
          "foreign_workers": 6,
          "wages": 363.79,
          "tax": 25.1,
          "irish_worker_tax": 7.63,
          "foreign_worker_tax": 17.47,
          "manual_rebate_due": 0.0,
          "host_retained": 17.57,
          "irish_rebate": 0,
          "foreign_rebate": 0,
          "deal_version": 1
        },
        {
          "id": "6813b6d546e731854c7ac8d7",
          "name": "Afghanistan",
          "code": "af",
          "rate": 6.19,
          "factories": 5,
          "workers": 6,
          "irish_workers": 2,
          "foreign_workers": 4,
          "wages": 402.54,
          "tax": 24.92,
          "irish_worker_tax": 7.57,
          "foreign_worker_tax": 17.35,
          "manual_rebate_due": 0.0,
          "host_retained": 17.44,
          "irish_rebate": 0,
          "foreign_rebate": 0,
          "deal_version": 1
        },
        {
          "id": "6873d0ea1758b40e712b5f28",
          "name": "DR Congo",
          "code": "cd",
          "rate": 5.0,
          "factories": 8,
          "workers": 9,
          "irish_workers": 2,
          "foreign_workers": 7,
          "wages": 324.44,
          "tax": 16.22,
          "irish_worker_tax": 10.46,
          "foreign_worker_tax": 5.77,
          "manual_rebate_due": 0.0,
          "host_retained": 11.36,
          "irish_rebate": 0,
          "foreign_rebate": 0,
          "deal_version": 1
        },
        {
          "id": "6813b6d546e731854c7ac82f",
          "name": "Brazil",
          "code": "br",
          "rate": 5.0,
          "factories": 7,
          "workers": 9,
          "irish_workers": 6,
          "foreign_workers": 3,
          "wages": 259.93,
          "tax": 13.0,
          "irish_worker_tax": 4.35,
          "foreign_worker_tax": 8.64,
          "manual_rebate_due": 0.0,
          "host_retained": 9.1,
          "irish_rebate": 0,
          "foreign_rebate": 0,
          "deal_version": 1
        },
        {
          "id": "6813b6d546e731854c7ac855",
          "name": "Ecuador",
          "code": "ec",
          "rate": 6.0,
          "factories": 3,
          "workers": 3,
          "irish_workers": 1,
          "foreign_workers": 2,
          "wages": 189.0,
          "tax": 11.34,
          "irish_worker_tax": 0.49,
          "foreign_worker_tax": 10.85,
          "manual_rebate_due": 0.0,
          "host_retained": 7.94,
          "irish_rebate": 0,
          "foreign_rebate": 0,
          "deal_version": 1
        },
        {
          "id": "6873d0ea1758b40e712b5ef5",
          "name": "Cameroon",
          "code": "cm",
          "rate": 5.0,
          "factories": 5,
          "workers": 5,
          "irish_workers": 3,
          "foreign_workers": 2,
          "wages": 205.82,
          "tax": 10.29,
          "irish_worker_tax": 4.64,
          "foreign_worker_tax": 5.65,
          "manual_rebate_due": 0.0,
          "host_retained": 7.2,
          "irish_rebate": 0,
          "foreign_rebate": 0,
          "deal_version": 1
        },
        {
          "id": "6813b6d546e731854c7ac890",
          "name": "Greenland",
          "code": "gl",
          "rate": 10.0,
          "factories": 2,
          "workers": 2,
          "irish_workers": 0,
          "foreign_workers": 2,
          "wages": 76.65,
          "tax": 7.67,
          "irish_worker_tax": 0.0,
          "foreign_worker_tax": 7.67,
          "manual_rebate_due": 0.0,
          "host_retained": 5.37,
          "irish_rebate": 0,
          "foreign_rebate": 0,
          "deal_version": 1
        },
        {
          "id": "6813b6d446e731854c7ac7f8",
          "name": "Mexico",
          "code": "mx",
          "rate": 4.0,
          "factories": 2,
          "workers": 3,
          "irish_workers": 0,
          "foreign_workers": 3,
          "wages": 180.65,
          "tax": 7.23,
          "irish_worker_tax": 0.0,
          "foreign_worker_tax": 7.23,
          "manual_rebate_due": 0.0,
          "host_retained": 5.06,
          "irish_rebate": 0,
          "foreign_rebate": 0,
          "deal_version": 1
        },
        {
          "id": "6813b6d446e731854c7ac7c0",
          "name": "Latvia",
          "code": "lv",
          "rate": 7.0,
          "factories": 3,
          "workers": 3,
          "irish_workers": 2,
          "foreign_workers": 1,
          "wages": 85.96,
          "tax": 6.02,
          "irish_worker_tax": 1.12,
          "foreign_worker_tax": 4.9,
          "manual_rebate_due": 0.0,
          "host_retained": 4.21,
          "irish_rebate": 0,
          "foreign_rebate": 0,
          "deal_version": 1
        },
        {
          "id": "683ddd2c24b5a2e114af1603",
          "name": "Somalia",
          "code": "so",
          "rate": 5.0,
          "factories": 1,
          "workers": 1,
          "irish_workers": 1,
          "foreign_workers": 0,
          "wages": 120.42,
          "tax": 6.02,
          "irish_worker_tax": 6.02,
          "foreign_worker_tax": 0.0,
          "manual_rebate_due": 0.0,
          "host_retained": 4.21,
          "irish_rebate": 0,
          "foreign_rebate": 0,
          "deal_version": 1
        },
        {
          "id": "683ddd2c24b5a2e114af15d9",
          "name": "Malaysia",
          "code": "my",
          "rate": 3.0,
          "factories": 3,
          "workers": 5,
          "irish_workers": 1,
          "foreign_workers": 4,
          "wages": 148.71,
          "tax": 4.46,
          "irish_worker_tax": 2.66,
          "foreign_worker_tax": 1.8,
          "manual_rebate_due": 0.0,
          "host_retained": 3.12,
          "irish_rebate": 0,
          "foreign_rebate": 0,
          "deal_version": 1
        },
        {
          "id": "6813b6d546e731854c7ac8b2",
          "name": "El Salvador",
          "code": "sv",
          "rate": 3.0,
          "factories": 2,
          "workers": 2,
          "irish_workers": 0,
          "foreign_workers": 2,
          "wages": 144.42,
          "tax": 4.33,
          "irish_worker_tax": 0.0,
          "foreign_worker_tax": 4.33,
          "manual_rebate_due": 0.0,
          "host_retained": 3.03,
          "irish_rebate": 0,
          "foreign_rebate": 0,
          "deal_version": 1
        },
        {
          "id": "6813b6d446e731854c7ac7b8",
          "name": "Lithuania",
          "code": "lt",
          "rate": 7.0,
          "factories": 1,
          "workers": 1,
          "irish_workers": 1,
          "foreign_workers": 0,
          "wages": 59.78,
          "tax": 4.18,
          "irish_worker_tax": 4.18,
          "foreign_worker_tax": 0.0,
          "manual_rebate_due": 0.0,
          "host_retained": 2.93,
          "irish_rebate": 0,
          "foreign_rebate": 0,
          "deal_version": 1
        },
        {
          "id": "6813b6d546e731854c7ac820",
          "name": "China",
          "code": "cn",
          "rate": 5.0,
          "factories": 2,
          "workers": 3,
          "irish_workers": 1,
          "foreign_workers": 2,
          "wages": 82.47,
          "tax": 4.12,
          "irish_worker_tax": 4.12,
          "foreign_worker_tax": 0.0,
          "manual_rebate_due": 0.0,
          "host_retained": 2.89,
          "irish_rebate": 0,
          "foreign_rebate": 0,
          "deal_version": 1
        },
        {
          "id": "6813b6d446e731854c7ac7a8",
          "name": "Spain",
          "code": "es",
          "rate": 4.0,
          "factories": 2,
          "workers": 2,
          "irish_workers": 1,
          "foreign_workers": 1,
          "wages": 98.98,
          "tax": 3.96,
          "irish_worker_tax": 1.33,
          "foreign_worker_tax": 2.63,
          "manual_rebate_due": 0.0,
          "host_retained": 2.77,
          "irish_rebate": 0,
          "foreign_rebate": 0,
          "deal_version": 1
        },
        {
          "id": "683ddd2c24b5a2e114af15d5",
          "name": "Myanmar",
          "code": "mm",
          "rate": 5.0,
          "factories": 1,
          "workers": 1,
          "irish_workers": 1,
          "foreign_workers": 0,
          "wages": 74.2,
          "tax": 3.71,
          "irish_worker_tax": 3.71,
          "foreign_worker_tax": 0.0,
          "manual_rebate_due": 0.0,
          "host_retained": 2.6,
          "irish_rebate": 0,
          "foreign_rebate": 0,
          "deal_version": 1
        },
        {
          "id": "6813b6d446e731854c7ac80b",
          "name": "Finland",
          "code": "fi",
          "rate": 7.0,
          "factories": 1,
          "workers": 1,
          "irish_workers": 0,
          "foreign_workers": 1,
          "wages": 37.52,
          "tax": 2.63,
          "irish_worker_tax": 0.0,
          "foreign_worker_tax": 2.63,
          "manual_rebate_due": 0.0,
          "host_retained": 1.84,
          "irish_rebate": 0,
          "foreign_rebate": 0,
          "deal_version": 1
        },
        {
          "id": "683ddd2c24b5a2e114af1606",
          "name": "Syria",
          "code": "sy",
          "rate": 3.0,
          "factories": 1,
          "workers": 3,
          "irish_workers": 0,
          "foreign_workers": 3,
          "wages": 84.96,
          "tax": 2.55,
          "irish_worker_tax": 0.0,
          "foreign_worker_tax": 2.55,
          "manual_rebate_due": 0.0,
          "host_retained": 1.78,
          "irish_rebate": 0,
          "foreign_rebate": 0,
          "deal_version": 1
        },
        {
          "id": "6813b6d446e731854c7ac7a2",
          "name": "Italy",
          "code": "it",
          "rate": 7.9,
          "factories": 1,
          "workers": 1,
          "irish_workers": 0,
          "foreign_workers": 1,
          "wages": 30.9,
          "tax": 2.44,
          "irish_worker_tax": 0.0,
          "foreign_worker_tax": 2.44,
          "manual_rebate_due": 0.0,
          "host_retained": 1.71,
          "irish_rebate": 0,
          "foreign_rebate": 0,
          "deal_version": 1
        },
        {
          "id": "696a81da63e2489f47e5a28a",
          "name": "Comoros",
          "code": "km",
          "rate": 4.0,
          "factories": 1,
          "workers": 1,
          "irish_workers": 1,
          "foreign_workers": 0,
          "wages": 59.89,
          "tax": 2.4,
          "irish_worker_tax": 2.4,
          "foreign_worker_tax": 0.0,
          "manual_rebate_due": 0.0,
          "host_retained": 1.68,
          "irish_rebate": 0,
          "foreign_rebate": 0,
          "deal_version": 1
        },
        {
          "id": "6813b6d546e731854c7ac880",
          "name": "New Zealand",
          "code": "nz",
          "rate": 3.9,
          "factories": 1,
          "workers": 1,
          "irish_workers": 1,
          "foreign_workers": 0,
          "wages": 51.41,
          "tax": 2.0,
          "irish_worker_tax": 2.0,
          "foreign_worker_tax": 0.0,
          "manual_rebate_due": 0.0,
          "host_retained": 1.4,
          "irish_rebate": 0,
          "foreign_rebate": 0,
          "deal_version": 1
        },
        {
          "id": "683ddd2c24b5a2e114af15c5",
          "name": "Iceland",
          "code": "is",
          "rate": 10.0,
          "factories": 1,
          "workers": 1,
          "irish_workers": 1,
          "foreign_workers": 0,
          "wages": 12.51,
          "tax": 1.25,
          "irish_worker_tax": 1.25,
          "foreign_worker_tax": 0.0,
          "manual_rebate_due": 0.0,
          "host_retained": 0.88,
          "irish_rebate": 0,
          "foreign_rebate": 0,
          "deal_version": 1
        },
        {
          "id": "6813b6d446e731854c7ac808",
          "name": "Canada",
          "code": "ca",
          "rate": 6.0,
          "factories": 1,
          "workers": 2,
          "irish_workers": 0,
          "foreign_workers": 2,
          "wages": 20.12,
          "tax": 1.21,
          "irish_worker_tax": 0.0,
          "foreign_worker_tax": 1.21,
          "manual_rebate_due": 0.0,
          "host_retained": 0.84,
          "irish_rebate": 0,
          "foreign_rebate": 0,
          "deal_version": 1
        },
        {
          "id": "6813b6d446e731854c7ac7fe",
          "name": "Ireland",
          "code": "ie",
          "rate": 4.0,
          "factories": 1,
          "workers": 4,
          "irish_workers": 2,
          "foreign_workers": 2,
          "wages": 28.77,
          "tax": 1.15,
          "irish_worker_tax": 0.0,
          "foreign_worker_tax": 1.15,
          "manual_rebate_due": 0.0,
          "host_retained": 0.81,
          "irish_rebate": 0,
          "foreign_rebate": 0,
          "deal_version": 1
        },
        {
          "id": "6813b6d546e731854c7ac8af",
          "name": "Nicaragua",
          "code": "ni",
          "rate": 4.0,
          "factories": 2,
          "workers": 4,
          "irish_workers": 0,
          "foreign_workers": 4,
          "wages": 14.06,
          "tax": 0.56,
          "irish_worker_tax": 0.0,
          "foreign_worker_tax": 0.56,
          "manual_rebate_due": 0.0,
          "host_retained": 0.39,
          "irish_rebate": 0,
          "foreign_rebate": 0,
          "deal_version": 1
        },
        {
          "id": "6813b6d546e731854c7ac842",
          "name": "Cyprus",
          "code": "cy",
          "rate": 6.0,
          "factories": 1,
          "workers": 1,
          "irish_workers": 0,
          "foreign_workers": 1,
          "wages": 8.8,
          "tax": 0.53,
          "irish_worker_tax": 0.0,
          "foreign_worker_tax": 0.53,
          "manual_rebate_due": 0.0,
          "host_retained": 0.37,
          "irish_rebate": 0,
          "foreign_rebate": 0,
          "deal_version": 1
        },
        {
          "id": "6813b6d546e731854c7ac865",
          "name": "Ukraine",
          "code": "ua",
          "rate": 10.0,
          "factories": 1,
          "workers": 1,
          "irish_workers": 1,
          "foreign_workers": 0,
          "wages": 5.19,
          "tax": 0.52,
          "irish_worker_tax": 0.52,
          "foreign_worker_tax": 0.0,
          "manual_rebate_due": 0.0,
          "host_retained": 0.36,
          "irish_rebate": 0,
          "foreign_rebate": 0,
          "deal_version": 1
        },
        {
          "id": "6813b6d546e731854c7ac871",
          "name": "Singapore",
          "code": "sg",
          "rate": 5.0,
          "factories": 1,
          "workers": 1,
          "irish_workers": 1,
          "foreign_workers": 0,
          "wages": 9.38,
          "tax": 0.47,
          "irish_worker_tax": 0.47,
          "foreign_worker_tax": 0.0,
          "manual_rebate_due": 0.0,
          "host_retained": 0.33,
          "irish_rebate": 0,
          "foreign_rebate": 0,
          "deal_version": 1
        },
        {
          "id": "683ddd2c24b5a2e114af15bf",
          "name": "Georgia",
          "code": "ge",
          "rate": 3.0,
          "factories": 1,
          "workers": 1,
          "irish_workers": 1,
          "foreign_workers": 0,
          "wages": 7.42,
          "tax": 0.22,
          "irish_worker_tax": 0.22,
          "foreign_worker_tax": 0.0,
          "manual_rebate_due": 0.0,
          "host_retained": 0.16,
          "irish_rebate": 0,
          "foreign_rebate": 0,
          "deal_version": 1
        },
        {
          "id": "6813b6d446e731854c7ac7a4",
          "name": "Belgium",
          "code": "be",
          "rate": 10.0,
          "factories": 1,
          "workers": 1,
          "irish_workers": 0,
          "foreign_workers": 1,
          "wages": 0.0,
          "tax": 0.0,
          "irish_worker_tax": 0.0,
          "foreign_worker_tax": 0.0,
          "manual_rebate_due": 0.0,
          "host_retained": 0.0,
          "irish_rebate": 0,
          "foreign_rebate": 0,
          "deal_version": 1
        },
        {
          "id": "6873d0ea1758b40e712b5f73",
          "name": "Zambia",
          "code": "zm",
          "rate": 4.0,
          "factories": 1,
          "workers": 1,
          "irish_workers": 0,
          "foreign_workers": 1,
          "wages": 0.0,
          "tax": 0.0,
          "irish_worker_tax": 0.0,
          "foreign_worker_tax": 0.0,
          "manual_rebate_due": 0.0,
          "host_retained": 0.0,
          "irish_rebate": 0,
          "foreign_rebate": 0,
          "deal_version": 1
        }
      ]
    },
    {
      "date": "2026-07-21",
      "countries": [
        {
          "id": "683ddd2c24b5a2e114af160f",
          "name": "Yemen",
          "code": "ye",
          "rate": 5.0,
          "factories": 47,
          "workers": 72,
          "irish_workers": 22,
          "foreign_workers": 50,
          "wages": 2638.7,
          "tax": 131.94,
          "irish_worker_tax": 48.03,
          "foreign_worker_tax": 83.9,
          "manual_rebate_due": 43.47,
          "host_retained": 48.88,
          "irish_rebate": 0.25,
          "foreign_rebate": 0.375,
          "deal_version": 1
        },
        {
          "id": "6813b6d446e731854c7ac7ba",
          "name": "Serbia",
          "code": "rs",
          "rate": 10.0,
          "factories": 24,
          "workers": 24,
          "irish_workers": 8,
          "foreign_workers": 16,
          "wages": 1081.35,
          "tax": 108.13,
          "irish_worker_tax": 27.47,
          "foreign_worker_tax": 80.66,
          "manual_rebate_due": 0.0,
          "host_retained": 75.69,
          "irish_rebate": 0,
          "foreign_rebate": 0,
          "deal_version": 1
        },
        {
          "id": "6813b6d546e731854c7ac862",
          "name": "India",
          "code": "in",
          "rate": 4.0,
          "factories": 18,
          "workers": 22,
          "irish_workers": 8,
          "foreign_workers": 14,
          "wages": 1297.16,
          "tax": 51.89,
          "irish_worker_tax": 20.7,
          "foreign_worker_tax": 31.19,
          "manual_rebate_due": 0.0,
          "host_retained": 36.32,
          "irish_rebate": 0,
          "foreign_rebate": 0,
          "deal_version": 1
        },
        {
          "id": "6873d0ea1758b40e712b5f16",
          "name": "Djibouti",
          "code": "dj",
          "rate": 7.5,
          "factories": 14,
          "workers": 17,
          "irish_workers": 6,
          "foreign_workers": 11,
          "wages": 513.27,
          "tax": 38.5,
          "irish_worker_tax": 29.0,
          "foreign_worker_tax": 9.49,
          "manual_rebate_due": 0.0,
          "host_retained": 26.95,
          "irish_rebate": 0,
          "foreign_rebate": 0,
          "deal_version": 1
        },
        {
          "id": "683ddd2c24b5a2e114af15f7",
          "name": "Namibia",
          "code": "na",
          "rate": 6.9,
          "factories": 9,
          "workers": 9,
          "irish_workers": 3,
          "foreign_workers": 6,
          "wages": 471.3,
          "tax": 32.52,
          "irish_worker_tax": 14.32,
          "foreign_worker_tax": 18.2,
          "manual_rebate_due": 0.0,
          "host_retained": 22.76,
          "irish_rebate": 0,
          "foreign_rebate": 0,
          "deal_version": 1
        },
        {
          "id": "6873d0ea1758b40e712b5ef5",
          "name": "Cameroon",
          "code": "cm",
          "rate": 15.0,
          "factories": 5,
          "workers": 5,
          "irish_workers": 3,
          "foreign_workers": 2,
          "wages": 190.76,
          "tax": 28.61,
          "irish_worker_tax": 14.66,
          "foreign_worker_tax": 13.95,
          "manual_rebate_due": 0.0,
          "host_retained": 20.03,
          "irish_rebate": 0,
          "foreign_rebate": 0,
          "deal_version": 1
        },
        {
          "id": "6813b6d546e731854c7ac8d7",
          "name": "Afghanistan",
          "code": "af",
          "rate": 6.19,
          "factories": 5,
          "workers": 6,
          "irish_workers": 2,
          "foreign_workers": 4,
          "wages": 372.25,
          "tax": 23.04,
          "irish_worker_tax": 6.85,
          "foreign_worker_tax": 16.19,
          "manual_rebate_due": 0.0,
          "host_retained": 16.13,
          "irish_rebate": 0,
          "foreign_rebate": 0,
          "deal_version": 1
        },
        {
          "id": "6813b6d546e731854c7ac82f",
          "name": "Brazil",
          "code": "br",
          "rate": 5.0,
          "factories": 7,
          "workers": 9,
          "irish_workers": 6,
          "foreign_workers": 3,
          "wages": 276.53,
          "tax": 13.83,
          "irish_worker_tax": 6.14,
          "foreign_worker_tax": 7.68,
          "manual_rebate_due": 0.0,
          "host_retained": 9.68,
          "irish_rebate": 0,
          "foreign_rebate": 0,
          "deal_version": 1
        },
        {
          "id": "6873d0ea1758b40e712b5f28",
          "name": "DR Congo",
          "code": "cd",
          "rate": 5.0,
          "factories": 5,
          "workers": 7,
          "irish_workers": 2,
          "foreign_workers": 5,
          "wages": 268.65,
          "tax": 13.43,
          "irish_worker_tax": 13.24,
          "foreign_worker_tax": 0.19,
          "manual_rebate_due": 0.0,
          "host_retained": 9.4,
          "irish_rebate": 0,
          "foreign_rebate": 0,
          "deal_version": 1
        },
        {
          "id": "6813b6d546e731854c7ac855",
          "name": "Ecuador",
          "code": "ec",
          "rate": 6.0,
          "factories": 3,
          "workers": 3,
          "irish_workers": 1,
          "foreign_workers": 2,
          "wages": 207.29,
          "tax": 12.44,
          "irish_worker_tax": 0.46,
          "foreign_worker_tax": 11.98,
          "manual_rebate_due": 0.0,
          "host_retained": 8.71,
          "irish_rebate": 0,
          "foreign_rebate": 0,
          "deal_version": 1
        },
        {
          "id": "6813b6d446e731854c7ac80b",
          "name": "Finland",
          "code": "fi",
          "rate": 7.0,
          "factories": 2,
          "workers": 2,
          "irish_workers": 0,
          "foreign_workers": 2,
          "wages": 159.81,
          "tax": 11.19,
          "irish_worker_tax": 0.0,
          "foreign_worker_tax": 11.19,
          "manual_rebate_due": 0.0,
          "host_retained": 7.83,
          "irish_rebate": 0,
          "foreign_rebate": 0,
          "deal_version": 1
        },
        {
          "id": "6813b6d446e731854c7ac7c0",
          "name": "Latvia",
          "code": "lv",
          "rate": 7.0,
          "factories": 3,
          "workers": 3,
          "irish_workers": 2,
          "foreign_workers": 1,
          "wages": 139.15,
          "tax": 9.74,
          "irish_worker_tax": 1.1,
          "foreign_worker_tax": 8.64,
          "manual_rebate_due": 0.0,
          "host_retained": 6.82,
          "irish_rebate": 0,
          "foreign_rebate": 0,
          "deal_version": 1
        },
        {
          "id": "683ddd2c24b5a2e114af15c5",
          "name": "Iceland",
          "code": "is",
          "rate": 10.0,
          "factories": 1,
          "workers": 1,
          "irish_workers": 1,
          "foreign_workers": 0,
          "wages": 83.21,
          "tax": 8.32,
          "irish_worker_tax": 8.32,
          "foreign_worker_tax": 0.0,
          "manual_rebate_due": 0.0,
          "host_retained": 5.82,
          "irish_rebate": 0,
          "foreign_rebate": 0,
          "deal_version": 1
        },
        {
          "id": "6813b6d546e731854c7ac890",
          "name": "Greenland",
          "code": "gl",
          "rate": 10.0,
          "factories": 2,
          "workers": 3,
          "irish_workers": 0,
          "foreign_workers": 3,
          "wages": 81.74,
          "tax": 8.17,
          "irish_worker_tax": 0.0,
          "foreign_worker_tax": 8.17,
          "manual_rebate_due": 0.0,
          "host_retained": 5.72,
          "irish_rebate": 0,
          "foreign_rebate": 0,
          "deal_version": 1
        },
        {
          "id": "6813b6d446e731854c7ac7a8",
          "name": "Spain",
          "code": "es",
          "rate": 4.0,
          "factories": 2,
          "workers": 2,
          "irish_workers": 1,
          "foreign_workers": 1,
          "wages": 146.09,
          "tax": 5.84,
          "irish_worker_tax": 1.93,
          "foreign_worker_tax": 3.91,
          "manual_rebate_due": 0.0,
          "host_retained": 4.09,
          "irish_rebate": 0,
          "foreign_rebate": 0,
          "deal_version": 1
        },
        {
          "id": "683ddd2c24b5a2e114af15d9",
          "name": "Malaysia",
          "code": "my",
          "rate": 3.0,
          "factories": 2,
          "workers": 2,
          "irish_workers": 1,
          "foreign_workers": 1,
          "wages": 174.49,
          "tax": 5.23,
          "irish_worker_tax": 2.95,
          "foreign_worker_tax": 2.28,
          "manual_rebate_due": 0.0,
          "host_retained": 3.66,
          "irish_rebate": 0,
          "foreign_rebate": 0,
          "deal_version": 1
        },
        {
          "id": "6813b6d446e731854c7ac7f8",
          "name": "Mexico",
          "code": "mx",
          "rate": 4.0,
          "factories": 2,
          "workers": 3,
          "irish_workers": 0,
          "foreign_workers": 3,
          "wages": 123.01,
          "tax": 4.92,
          "irish_worker_tax": 0.0,
          "foreign_worker_tax": 4.92,
          "manual_rebate_due": 0.0,
          "host_retained": 3.44,
          "irish_rebate": 0,
          "foreign_rebate": 0,
          "deal_version": 1
        },
        {
          "id": "683ddd2c24b5a2e114af1606",
          "name": "Syria",
          "code": "sy",
          "rate": 3.0,
          "factories": 1,
          "workers": 3,
          "irish_workers": 0,
          "foreign_workers": 3,
          "wages": 138.43,
          "tax": 4.15,
          "irish_worker_tax": 0.0,
          "foreign_worker_tax": 4.15,
          "manual_rebate_due": 0.0,
          "host_retained": 2.91,
          "irish_rebate": 0,
          "foreign_rebate": 0,
          "deal_version": 1
        },
        {
          "id": "6813b6d546e731854c7ac880",
          "name": "New Zealand",
          "code": "nz",
          "rate": 3.9,
          "factories": 1,
          "workers": 1,
          "irish_workers": 1,
          "foreign_workers": 0,
          "wages": 104.73,
          "tax": 4.08,
          "irish_worker_tax": 4.08,
          "foreign_worker_tax": 0.0,
          "manual_rebate_due": 0.0,
          "host_retained": 2.86,
          "irish_rebate": 0,
          "foreign_rebate": 0,
          "deal_version": 1
        },
        {
          "id": "6813b6d546e731854c7ac8b2",
          "name": "El Salvador",
          "code": "sv",
          "rate": 3.0,
          "factories": 2,
          "workers": 2,
          "irish_workers": 0,
          "foreign_workers": 2,
          "wages": 130.94,
          "tax": 3.93,
          "irish_worker_tax": 0.0,
          "foreign_worker_tax": 3.93,
          "manual_rebate_due": 0.0,
          "host_retained": 2.75,
          "irish_rebate": 0,
          "foreign_rebate": 0,
          "deal_version": 1
        },
        {
          "id": "6813b6d446e731854c7ac7b8",
          "name": "Lithuania",
          "code": "lt",
          "rate": 7.0,
          "factories": 1,
          "workers": 1,
          "irish_workers": 1,
          "foreign_workers": 0,
          "wages": 47.49,
          "tax": 3.32,
          "irish_worker_tax": 3.32,
          "foreign_worker_tax": 0.0,
          "manual_rebate_due": 0.0,
          "host_retained": 2.33,
          "irish_rebate": 0,
          "foreign_rebate": 0,
          "deal_version": 1
        },
        {
          "id": "6813b6d546e731854c7ac8b5",
          "name": "Honduras",
          "code": "hn",
          "rate": 4.0,
          "factories": 1,
          "workers": 1,
          "irish_workers": 0,
          "foreign_workers": 1,
          "wages": 76.05,
          "tax": 3.04,
          "irish_worker_tax": 0.0,
          "foreign_worker_tax": 3.04,
          "manual_rebate_due": 0.0,
          "host_retained": 2.13,
          "irish_rebate": 0,
          "foreign_rebate": 0,
          "deal_version": 1
        },
        {
          "id": "696a81da63e2489f47e5a28a",
          "name": "Comoros",
          "code": "km",
          "rate": 4.0,
          "factories": 1,
          "workers": 1,
          "irish_workers": 1,
          "foreign_workers": 0,
          "wages": 72.5,
          "tax": 2.9,
          "irish_worker_tax": 2.9,
          "foreign_worker_tax": 0.0,
          "manual_rebate_due": 0.0,
          "host_retained": 2.03,
          "irish_rebate": 0,
          "foreign_rebate": 0,
          "deal_version": 1
        },
        {
          "id": "683ddd2c24b5a2e114af1603",
          "name": "Somalia",
          "code": "so",
          "rate": 5.0,
          "factories": 1,
          "workers": 1,
          "irish_workers": 1,
          "foreign_workers": 0,
          "wages": 43.04,
          "tax": 2.15,
          "irish_worker_tax": 2.15,
          "foreign_worker_tax": 0.0,
          "manual_rebate_due": 0.0,
          "host_retained": 1.51,
          "irish_rebate": 0,
          "foreign_rebate": 0,
          "deal_version": 1
        },
        {
          "id": "6813b6d446e731854c7ac7fe",
          "name": "Ireland",
          "code": "ie",
          "rate": 4.0,
          "factories": 1,
          "workers": 4,
          "irish_workers": 1,
          "foreign_workers": 3,
          "wages": 48.32,
          "tax": 1.93,
          "irish_worker_tax": 1.26,
          "foreign_worker_tax": 0.68,
          "manual_rebate_due": 0.0,
          "host_retained": 1.35,
          "irish_rebate": 0,
          "foreign_rebate": 0,
          "deal_version": 1
        },
        {
          "id": "6813b6d446e731854c7ac7a2",
          "name": "Italy",
          "code": "it",
          "rate": 7.9,
          "factories": 1,
          "workers": 1,
          "irish_workers": 0,
          "foreign_workers": 1,
          "wages": 21.6,
          "tax": 1.71,
          "irish_worker_tax": 0.0,
          "foreign_worker_tax": 1.71,
          "manual_rebate_due": 0.0,
          "host_retained": 1.19,
          "irish_rebate": 0,
          "foreign_rebate": 0,
          "deal_version": 1
        },
        {
          "id": "6813b6d546e731854c7ac8af",
          "name": "Nicaragua",
          "code": "ni",
          "rate": 3.5,
          "factories": 2,
          "workers": 4,
          "irish_workers": 0,
          "foreign_workers": 4,
          "wages": 33.91,
          "tax": 1.19,
          "irish_worker_tax": 0.0,
          "foreign_worker_tax": 1.19,
          "manual_rebate_due": 0.0,
          "host_retained": 0.83,
          "irish_rebate": 0,
          "foreign_rebate": 0,
          "deal_version": 1
        },
        {
          "id": "6813b6d546e731854c7ac865",
          "name": "Ukraine",
          "code": "ua",
          "rate": 10.0,
          "factories": 1,
          "workers": 1,
          "irish_workers": 1,
          "foreign_workers": 0,
          "wages": 6.36,
          "tax": 0.64,
          "irish_worker_tax": 0.64,
          "foreign_worker_tax": 0.0,
          "manual_rebate_due": 0.0,
          "host_retained": 0.45,
          "irish_rebate": 0,
          "foreign_rebate": 0,
          "deal_version": 1
        },
        {
          "id": "6813b6d546e731854c7ac842",
          "name": "Cyprus",
          "code": "cy",
          "rate": 6.0,
          "factories": 2,
          "workers": 2,
          "irish_workers": 0,
          "foreign_workers": 2,
          "wages": 7.53,
          "tax": 0.45,
          "irish_worker_tax": 0.0,
          "foreign_worker_tax": 0.45,
          "manual_rebate_due": 0.0,
          "host_retained": 0.32,
          "irish_rebate": 0,
          "foreign_rebate": 0,
          "deal_version": 1
        },
        {
          "id": "6813b6d546e731854c7ac871",
          "name": "Singapore",
          "code": "sg",
          "rate": 5.0,
          "factories": 1,
          "workers": 1,
          "irish_workers": 1,
          "foreign_workers": 0,
          "wages": 8.26,
          "tax": 0.41,
          "irish_worker_tax": 0.41,
          "foreign_worker_tax": 0.0,
          "manual_rebate_due": 0.0,
          "host_retained": 0.29,
          "irish_rebate": 0,
          "foreign_rebate": 0,
          "deal_version": 1
        },
        {
          "id": "683ddd2c24b5a2e114af15bf",
          "name": "Georgia",
          "code": "ge",
          "rate": 3.0,
          "factories": 1,
          "workers": 1,
          "irish_workers": 1,
          "foreign_workers": 0,
          "wages": 7.42,
          "tax": 0.22,
          "irish_worker_tax": 0.22,
          "foreign_worker_tax": 0.0,
          "manual_rebate_due": 0.0,
          "host_retained": 0.16,
          "irish_rebate": 0,
          "foreign_rebate": 0,
          "deal_version": 1
        },
        {
          "id": "6813b6d446e731854c7ac7a4",
          "name": "Belgium",
          "code": "be",
          "rate": 10.0,
          "factories": 1,
          "workers": 1,
          "irish_workers": 0,
          "foreign_workers": 1,
          "wages": 0.0,
          "tax": 0.0,
          "irish_worker_tax": 0.0,
          "foreign_worker_tax": 0.0,
          "manual_rebate_due": 0.0,
          "host_retained": 0.0,
          "irish_rebate": 0,
          "foreign_rebate": 0,
          "deal_version": 1
        },
        {
          "id": "6873d0ea1758b40e712b5f73",
          "name": "Zambia",
          "code": "zm",
          "rate": 4.0,
          "factories": 1,
          "workers": 1,
          "irish_workers": 0,
          "foreign_workers": 1,
          "wages": 0.0,
          "tax": 0.0,
          "irish_worker_tax": 0.0,
          "foreign_worker_tax": 0.0,
          "manual_rebate_due": 0.0,
          "host_retained": 0.0,
          "irish_rebate": 0,
          "foreign_rebate": 0,
          "deal_version": 1
        },
        {
          "id": "6813b6d546e731854c7ac820",
          "name": "China",
          "code": "cn",
          "rate": 5.0,
          "factories": 1,
          "workers": 2,
          "irish_workers": 0,
          "foreign_workers": 2,
          "wages": 0.0,
          "tax": 0.0,
          "irish_worker_tax": 0.0,
          "foreign_worker_tax": 0.0,
          "manual_rebate_due": 0.0,
          "host_retained": 0.0,
          "irish_rebate": 0,
          "foreign_rebate": 0,
          "deal_version": 1
        },
        {
          "id": "6873d0ea1758b40e712b5f37",
          "name": "Burkina Faso",
          "code": "bf",
          "rate": 7.0,
          "factories": 1,
          "workers": 3,
          "irish_workers": 0,
          "foreign_workers": 3,
          "wages": 0.0,
          "tax": 0.0,
          "irish_worker_tax": 0.0,
          "foreign_worker_tax": 0.0,
          "manual_rebate_due": 0.0,
          "host_retained": 0.0,
          "irish_rebate": 0,
          "foreign_rebate": 0,
          "deal_version": 1
        }
      ]
    },
    {
      "date": "2026-07-22",
      "countries": [
        {
          "id": "683ddd2c24b5a2e114af160f",
          "name": "Yemen",
          "code": "ye",
          "rate": 5.0,
          "factories": 49,
          "workers": 74,
          "irish_workers": 24,
          "foreign_workers": 50,
          "wages": 2754.93,
          "tax": 137.75,
          "irish_worker_tax": 52.64,
          "foreign_worker_tax": 85.1,
          "manual_rebate_due": 45.07,
          "host_retained": 51.35,
          "irish_rebate": 0.25,
          "foreign_rebate": 0.375,
          "deal_version": 1
        },
        {
          "id": "6813b6d446e731854c7ac7ba",
          "name": "Serbia",
          "code": "rs",
          "rate": 10.0,
          "factories": 28,
          "workers": 29,
          "irish_workers": 10,
          "foreign_workers": 19,
          "wages": 1133.74,
          "tax": 113.37,
          "irish_worker_tax": 20.0,
          "foreign_worker_tax": 93.38,
          "manual_rebate_due": 0.0,
          "host_retained": 79.36,
          "irish_rebate": 0,
          "foreign_rebate": 0,
          "deal_version": 1
        },
        {
          "id": "6813b6d546e731854c7ac862",
          "name": "India",
          "code": "in",
          "rate": 7.5,
          "factories": 16,
          "workers": 19,
          "irish_workers": 5,
          "foreign_workers": 14,
          "wages": 1343.3,
          "tax": 100.75,
          "irish_worker_tax": 31.66,
          "foreign_worker_tax": 69.09,
          "manual_rebate_due": 0.0,
          "host_retained": 70.52,
          "irish_rebate": 0,
          "foreign_rebate": 0,
          "deal_version": 1
        },
        {
          "id": "6873d0ea1758b40e712b5f16",
          "name": "Djibouti",
          "code": "dj",
          "rate": 7.5,
          "factories": 14,
          "workers": 18,
          "irish_workers": 6,
          "foreign_workers": 12,
          "wages": 462.33,
          "tax": 34.67,
          "irish_worker_tax": 24.25,
          "foreign_worker_tax": 10.42,
          "manual_rebate_due": 0.0,
          "host_retained": 24.27,
          "irish_rebate": 0,
          "foreign_rebate": 0,
          "deal_version": 1
        },
        {
          "id": "6813b6d546e731854c7ac8d7",
          "name": "Afghanistan",
          "code": "af",
          "rate": 6.19,
          "factories": 6,
          "workers": 7,
          "irish_workers": 3,
          "foreign_workers": 4,
          "wages": 421.01,
          "tax": 26.06,
          "irish_worker_tax": 6.48,
          "foreign_worker_tax": 19.58,
          "manual_rebate_due": 0.0,
          "host_retained": 18.24,
          "irish_rebate": 0,
          "foreign_rebate": 0,
          "deal_version": 1
        },
        {
          "id": "683ddd2c24b5a2e114af15f7",
          "name": "Namibia",
          "code": "na",
          "rate": 6.9,
          "factories": 8,
          "workers": 8,
          "irish_workers": 5,
          "foreign_workers": 3,
          "wages": 334.05,
          "tax": 23.05,
          "irish_worker_tax": 12.7,
          "foreign_worker_tax": 10.35,
          "manual_rebate_due": 0.0,
          "host_retained": 16.13,
          "irish_rebate": 0,
          "foreign_rebate": 0,
          "deal_version": 1
        },
        {
          "id": "6873d0ea1758b40e712b5f28",
          "name": "DR Congo",
          "code": "cd",
          "rate": 5.0,
          "factories": 6,
          "workers": 7,
          "irish_workers": 2,
          "foreign_workers": 5,
          "wages": 269.71,
          "tax": 13.49,
          "irish_worker_tax": 12.48,
          "foreign_worker_tax": 1.01,
          "manual_rebate_due": 0.0,
          "host_retained": 9.44,
          "irish_rebate": 0,
          "foreign_rebate": 0,
          "deal_version": 1
        },
        {
          "id": "6813b6d446e731854c7ac80b",
          "name": "Finland",
          "code": "fi",
          "rate": 7.0,
          "factories": 2,
          "workers": 2,
          "irish_workers": 0,
          "foreign_workers": 2,
          "wages": 176.27,
          "tax": 12.34,
          "irish_worker_tax": 0.0,
          "foreign_worker_tax": 12.34,
          "manual_rebate_due": 0.0,
          "host_retained": 8.64,
          "irish_rebate": 0,
          "foreign_rebate": 0,
          "deal_version": 1
        },
        {
          "id": "6813b6d546e731854c7ac82f",
          "name": "Brazil",
          "code": "br",
          "rate": 5.0,
          "factories": 7,
          "workers": 9,
          "irish_workers": 6,
          "foreign_workers": 3,
          "wages": 236.54,
          "tax": 11.83,
          "irish_worker_tax": 7.14,
          "foreign_worker_tax": 4.69,
          "manual_rebate_due": 0.0,
          "host_retained": 8.28,
          "irish_rebate": 0,
          "foreign_rebate": 0,
          "deal_version": 1
        },
        {
          "id": "683ddd2c24b5a2e114af15c5",
          "name": "Iceland",
          "code": "is",
          "rate": 10.0,
          "factories": 2,
          "workers": 3,
          "irish_workers": 1,
          "foreign_workers": 2,
          "wages": 115.15,
          "tax": 11.52,
          "irish_worker_tax": 6.7,
          "foreign_worker_tax": 4.82,
          "manual_rebate_due": 0.0,
          "host_retained": 8.06,
          "irish_rebate": 0,
          "foreign_rebate": 0,
          "deal_version": 1
        },
        {
          "id": "6813b6d446e731854c7ac7c0",
          "name": "Latvia",
          "code": "lv",
          "rate": 7.0,
          "factories": 3,
          "workers": 3,
          "irish_workers": 2,
          "foreign_workers": 1,
          "wages": 120.01,
          "tax": 8.4,
          "irish_worker_tax": 1.17,
          "foreign_worker_tax": 7.23,
          "manual_rebate_due": 0.0,
          "host_retained": 5.88,
          "irish_rebate": 0,
          "foreign_rebate": 0,
          "deal_version": 1
        },
        {
          "id": "6813b6d446e731854c7ac7f8",
          "name": "Mexico",
          "code": "mx",
          "rate": 4.0,
          "factories": 2,
          "workers": 3,
          "irish_workers": 0,
          "foreign_workers": 3,
          "wages": 187.07,
          "tax": 7.48,
          "irish_worker_tax": 0.0,
          "foreign_worker_tax": 7.48,
          "manual_rebate_due": 0.0,
          "host_retained": 5.24,
          "irish_rebate": 0,
          "foreign_rebate": 0,
          "deal_version": 1
        },
        {
          "id": "6813b6d546e731854c7ac855",
          "name": "Ecuador",
          "code": "ec",
          "rate": 6.0,
          "factories": 1,
          "workers": 1,
          "irish_workers": 0,
          "foreign_workers": 1,
          "wages": 112.84,
          "tax": 6.77,
          "irish_worker_tax": 0.0,
          "foreign_worker_tax": 6.77,
          "manual_rebate_due": 0.0,
          "host_retained": 4.74,
          "irish_rebate": 0,
          "foreign_rebate": 0,
          "deal_version": 1
        },
        {
          "id": "6873d0ea1758b40e712b5ef5",
          "name": "Cameroon",
          "code": "cm",
          "rate": 15.0,
          "factories": 5,
          "workers": 5,
          "irish_workers": 3,
          "foreign_workers": 2,
          "wages": 34.14,
          "tax": 5.12,
          "irish_worker_tax": 4.58,
          "foreign_worker_tax": 0.54,
          "manual_rebate_due": 0.0,
          "host_retained": 3.58,
          "irish_rebate": 0,
          "foreign_rebate": 0,
          "deal_version": 1
        },
        {
          "id": "6813b6d446e731854c7ac808",
          "name": "Canada",
          "code": "ca",
          "rate": 6.0,
          "factories": 1,
          "workers": 2,
          "irish_workers": 1,
          "foreign_workers": 1,
          "wages": 84.94,
          "tax": 5.1,
          "irish_worker_tax": 0.9,
          "foreign_worker_tax": 4.2,
          "manual_rebate_due": 0.0,
          "host_retained": 3.57,
          "irish_rebate": 0,
          "foreign_rebate": 0,
          "deal_version": 1
        },
        {
          "id": "6813b6d546e731854c7ac890",
          "name": "Greenland",
          "code": "gl",
          "rate": 10.0,
          "factories": 1,
          "workers": 1,
          "irish_workers": 0,
          "foreign_workers": 1,
          "wages": 50.11,
          "tax": 5.01,
          "irish_worker_tax": 0.0,
          "foreign_worker_tax": 5.01,
          "manual_rebate_due": 0.0,
          "host_retained": 3.51,
          "irish_rebate": 0,
          "foreign_rebate": 0,
          "deal_version": 1
        },
        {
          "id": "6813b6d546e731854c7ac8b2",
          "name": "El Salvador",
          "code": "sv",
          "rate": 3.0,
          "factories": 2,
          "workers": 2,
          "irish_workers": 0,
          "foreign_workers": 2,
          "wages": 166.96,
          "tax": 5.01,
          "irish_worker_tax": 0.0,
          "foreign_worker_tax": 5.01,
          "manual_rebate_due": 0.0,
          "host_retained": 3.51,
          "irish_rebate": 0,
          "foreign_rebate": 0,
          "deal_version": 1
        },
        {
          "id": "6813b6d546e731854c7ac8b5",
          "name": "Honduras",
          "code": "hn",
          "rate": 4.0,
          "factories": 2,
          "workers": 2,
          "irish_workers": 0,
          "foreign_workers": 2,
          "wages": 115.08,
          "tax": 4.6,
          "irish_worker_tax": 0.0,
          "foreign_worker_tax": 4.6,
          "manual_rebate_due": 0.0,
          "host_retained": 3.22,
          "irish_rebate": 0,
          "foreign_rebate": 0,
          "deal_version": 1
        },
        {
          "id": "6813b6d446e731854c7ac7a8",
          "name": "Spain",
          "code": "es",
          "rate": 4.0,
          "factories": 2,
          "workers": 2,
          "irish_workers": 1,
          "foreign_workers": 1,
          "wages": 114.3,
          "tax": 4.57,
          "irish_worker_tax": 1.58,
          "foreign_worker_tax": 2.99,
          "manual_rebate_due": 0.0,
          "host_retained": 3.2,
          "irish_rebate": 0,
          "foreign_rebate": 0,
          "deal_version": 1
        },
        {
          "id": "683ddd2c24b5a2e114af15d9",
          "name": "Malaysia",
          "code": "my",
          "rate": 3.0,
          "factories": 2,
          "workers": 2,
          "irish_workers": 1,
          "foreign_workers": 1,
          "wages": 140.0,
          "tax": 4.2,
          "irish_worker_tax": 2.56,
          "foreign_worker_tax": 1.64,
          "manual_rebate_due": 0.0,
          "host_retained": 2.94,
          "irish_rebate": 0,
          "foreign_rebate": 0,
          "deal_version": 1
        },
        {
          "id": "683ddd2c24b5a2e114af15bf",
          "name": "Georgia",
          "code": "ge",
          "rate": 3.0,
          "factories": 2,
          "workers": 2,
          "irish_workers": 1,
          "foreign_workers": 1,
          "wages": 110.31,
          "tax": 3.31,
          "irish_worker_tax": 0.26,
          "foreign_worker_tax": 3.05,
          "manual_rebate_due": 0.0,
          "host_retained": 2.32,
          "irish_rebate": 0,
          "foreign_rebate": 0,
          "deal_version": 1
        },
        {
          "id": "6813b6d446e731854c7ac7b8",
          "name": "Lithuania",
          "code": "lt",
          "rate": 7.0,
          "factories": 1,
          "workers": 1,
          "irish_workers": 1,
          "foreign_workers": 0,
          "wages": 36.46,
          "tax": 2.55,
          "irish_worker_tax": 2.55,
          "foreign_worker_tax": 0.0,
          "manual_rebate_due": 0.0,
          "host_retained": 1.79,
          "irish_rebate": 0,
          "foreign_rebate": 0,
          "deal_version": 1
        },
        {
          "id": "6813b6d446e731854c7ac7fe",
          "name": "Ireland",
          "code": "ie",
          "rate": 4.0,
          "factories": 1,
          "workers": 4,
          "irish_workers": 1,
          "foreign_workers": 3,
          "wages": 42.12,
          "tax": 1.68,
          "irish_worker_tax": 0.0,
          "foreign_worker_tax": 1.68,
          "manual_rebate_due": 0.0,
          "host_retained": 1.18,
          "irish_rebate": 0,
          "foreign_rebate": 0,
          "deal_version": 1
        },
        {
          "id": "6873d0ea1758b40e712b5f37",
          "name": "Burkina Faso",
          "code": "bf",
          "rate": 2.9,
          "factories": 3,
          "workers": 5,
          "irish_workers": 0,
          "foreign_workers": 5,
          "wages": 45.02,
          "tax": 1.31,
          "irish_worker_tax": 0.0,
          "foreign_worker_tax": 1.31,
          "manual_rebate_due": 0.0,
          "host_retained": 0.91,
          "irish_rebate": 0,
          "foreign_rebate": 0,
          "deal_version": 1
        },
        {
          "id": "6813b6d546e731854c7ac86e",
          "name": "Kenya",
          "code": "ke",
          "rate": 9.0,
          "factories": 1,
          "workers": 1,
          "irish_workers": 0,
          "foreign_workers": 1,
          "wages": 13.77,
          "tax": 1.24,
          "irish_worker_tax": 0.0,
          "foreign_worker_tax": 1.24,
          "manual_rebate_due": 0.0,
          "host_retained": 0.87,
          "irish_rebate": 0,
          "foreign_rebate": 0,
          "deal_version": 1
        },
        {
          "id": "6813b6d546e731854c7ac8af",
          "name": "Nicaragua",
          "code": "ni",
          "rate": 3.5,
          "factories": 2,
          "workers": 4,
          "irish_workers": 0,
          "foreign_workers": 4,
          "wages": 14.45,
          "tax": 0.51,
          "irish_worker_tax": 0.0,
          "foreign_worker_tax": 0.51,
          "manual_rebate_due": 0.0,
          "host_retained": 0.35,
          "irish_rebate": 0,
          "foreign_rebate": 0,
          "deal_version": 1
        },
        {
          "id": "6813b6d546e731854c7ac871",
          "name": "Singapore",
          "code": "sg",
          "rate": 5.0,
          "factories": 1,
          "workers": 1,
          "irish_workers": 1,
          "foreign_workers": 0,
          "wages": 9.66,
          "tax": 0.48,
          "irish_worker_tax": 0.48,
          "foreign_worker_tax": 0.0,
          "manual_rebate_due": 0.0,
          "host_retained": 0.34,
          "irish_rebate": 0,
          "foreign_rebate": 0,
          "deal_version": 1
        },
        {
          "id": "6813b6d546e731854c7ac842",
          "name": "Cyprus",
          "code": "cy",
          "rate": 6.0,
          "factories": 2,
          "workers": 2,
          "irish_workers": 0,
          "foreign_workers": 2,
          "wages": 7.42,
          "tax": 0.45,
          "irish_worker_tax": 0.0,
          "foreign_worker_tax": 0.45,
          "manual_rebate_due": 0.0,
          "host_retained": 0.31,
          "irish_rebate": 0,
          "foreign_rebate": 0,
          "deal_version": 1
        },
        {
          "id": "683ddd2c24b5a2e114af1606",
          "name": "Syria",
          "code": "sy",
          "rate": 3.0,
          "factories": 1,
          "workers": 3,
          "irish_workers": 0,
          "foreign_workers": 3,
          "wages": 14.35,
          "tax": 0.43,
          "irish_worker_tax": 0.0,
          "foreign_worker_tax": 0.43,
          "manual_rebate_due": 0.0,
          "host_retained": 0.3,
          "irish_rebate": 0,
          "foreign_rebate": 0,
          "deal_version": 1
        },
        {
          "id": "6813b6d546e731854c7ac880",
          "name": "New Zealand",
          "code": "nz",
          "rate": 3.9,
          "factories": 1,
          "workers": 1,
          "irish_workers": 1,
          "foreign_workers": 0,
          "wages": 7.31,
          "tax": 0.29,
          "irish_worker_tax": 0.29,
          "foreign_worker_tax": 0.0,
          "manual_rebate_due": 0.0,
          "host_retained": 0.2,
          "irish_rebate": 0,
          "foreign_rebate": 0,
          "deal_version": 1
        },
        {
          "id": "6813b6d546e731854c7ac820",
          "name": "China",
          "code": "cn",
          "rate": 5.0,
          "factories": 1,
          "workers": 1,
          "irish_workers": 1,
          "foreign_workers": 0,
          "wages": 0.0,
          "tax": 0.0,
          "irish_worker_tax": 0.0,
          "foreign_worker_tax": 0.0,
          "manual_rebate_due": 0.0,
          "host_retained": 0.0,
          "irish_rebate": 0,
          "foreign_rebate": 0,
          "deal_version": 1
        },
        {
          "id": "6813b6d446e731854c7ac7a4",
          "name": "Belgium",
          "code": "be",
          "rate": 10.0,
          "factories": 1,
          "workers": 1,
          "irish_workers": 0,
          "foreign_workers": 1,
          "wages": 0.0,
          "tax": 0.0,
          "irish_worker_tax": 0.0,
          "foreign_worker_tax": 0.0,
          "manual_rebate_due": 0.0,
          "host_retained": 0.0,
          "irish_rebate": 0,
          "foreign_rebate": 0,
          "deal_version": 1
        },
        {
          "id": "6873d0ea1758b40e712b5f73",
          "name": "Zambia",
          "code": "zm",
          "rate": 4.0,
          "factories": 1,
          "workers": 1,
          "irish_workers": 0,
          "foreign_workers": 1,
          "wages": 0.0,
          "tax": 0.0,
          "irish_worker_tax": 0.0,
          "foreign_worker_tax": 0.0,
          "manual_rebate_due": 0.0,
          "host_retained": 0.0,
          "irish_rebate": 0,
          "foreign_rebate": 0,
          "deal_version": 1
        },
        {
          "id": "683ddd2c24b5a2e114af1609",
          "name": "Thailand",
          "code": "th",
          "rate": 1.0,
          "factories": 1,
          "workers": 2,
          "irish_workers": 0,
          "foreign_workers": 2,
          "wages": 0.0,
          "tax": 0.0,
          "irish_worker_tax": 0.0,
          "foreign_worker_tax": 0.0,
          "manual_rebate_due": 0.0,
          "host_retained": 0.0,
          "irish_rebate": 0,
          "foreign_rebate": 0,
          "deal_version": 1
        }
      ]
    }
  ],
  "totals": {
    "683ddd2c24b5a2e114af160f": {
      "name": "Yemen",
      "code": "ye",
      "rate": 5.0,
      "factories": 142,
      "workers": 219,
      "irish_workers": 69,
      "foreign_workers": 150,
      "wages": 8096.02,
      "tax": 404.81,
      "irish_worker_tax": 154.8,
      "foreign_worker_tax": 249.98,
      "manual_rebate_due": 132.44,
      "host_retained": 150.91,
      "irish_rebate": 0.25,
      "foreign_rebate": 0.375,
      "deal_version": 1
    },
    "6813b6d446e731854c7ac7ba": {
      "name": "Serbia",
      "code": "rs",
      "rate": 10.0,
      "factories": 75,
      "workers": 76,
      "irish_workers": 25,
      "foreign_workers": 51,
      "wages": 3165.22,
      "tax": 316.51,
      "irish_worker_tax": 73.28,
      "foreign_worker_tax": 243.25,
      "manual_rebate_due": 0.0,
      "host_retained": 221.56,
      "irish_rebate": 0,
      "foreign_rebate": 0,
      "deal_version": 1
    },
    "6813b6d546e731854c7ac862": {
      "name": "India",
      "code": "in",
      "rate": 4.0,
      "factories": 48,
      "workers": 58,
      "irish_workers": 21,
      "foreign_workers": 37,
      "wages": 3635.35,
      "tax": 192.44,
      "irish_worker_tax": 70.89,
      "foreign_worker_tax": 121.55,
      "manual_rebate_due": 0.0,
      "host_retained": 134.7,
      "irish_rebate": 0,
      "foreign_rebate": 0,
      "deal_version": 1
    },
    "6873d0ea1758b40e712b5f16": {
      "name": "Djibouti",
      "code": "dj",
      "rate": 7.5,
      "factories": 41,
      "workers": 50,
      "irish_workers": 17,
      "foreign_workers": 33,
      "wages": 1426.16,
      "tax": 106.96,
      "irish_worker_tax": 78.53,
      "foreign_worker_tax": 28.42,
      "manual_rebate_due": 0.0,
      "host_retained": 74.87,
      "irish_rebate": 0,
      "foreign_rebate": 0,
      "deal_version": 1
    },
    "683ddd2c24b5a2e114af15f7": {
      "name": "Namibia",
      "code": "na",
      "rate": 6.9,
      "factories": 25,
      "workers": 25,
      "irish_workers": 10,
      "foreign_workers": 15,
      "wages": 1169.14,
      "tax": 80.67,
      "irish_worker_tax": 34.65,
      "foreign_worker_tax": 46.02,
      "manual_rebate_due": 0.0,
      "host_retained": 56.46,
      "irish_rebate": 0,
      "foreign_rebate": 0,
      "deal_version": 1
    },
    "6813b6d546e731854c7ac8d7": {
      "name": "Afghanistan",
      "code": "af",
      "rate": 6.19,
      "factories": 16,
      "workers": 19,
      "irish_workers": 7,
      "foreign_workers": 12,
      "wages": 1195.8,
      "tax": 74.02,
      "irish_worker_tax": 20.9,
      "foreign_worker_tax": 53.12,
      "manual_rebate_due": 0.0,
      "host_retained": 51.81,
      "irish_rebate": 0,
      "foreign_rebate": 0,
      "deal_version": 1
    },
    "6873d0ea1758b40e712b5f28": {
      "name": "DR Congo",
      "code": "cd",
      "rate": 5.0,
      "factories": 19,
      "workers": 23,
      "irish_workers": 6,
      "foreign_workers": 17,
      "wages": 862.8,
      "tax": 43.14,
      "irish_worker_tax": 36.18,
      "foreign_worker_tax": 6.97,
      "manual_rebate_due": 0.0,
      "host_retained": 30.2,
      "irish_rebate": 0,
      "foreign_rebate": 0,
      "deal_version": 1
    },
    "6813b6d546e731854c7ac82f": {
      "name": "Brazil",
      "code": "br",
      "rate": 5.0,
      "factories": 21,
      "workers": 27,
      "irish_workers": 18,
      "foreign_workers": 9,
      "wages": 773.0,
      "tax": 38.66,
      "irish_worker_tax": 17.63,
      "foreign_worker_tax": 21.01,
      "manual_rebate_due": 0.0,
      "host_retained": 27.06,
      "irish_rebate": 0,
      "foreign_rebate": 0,
      "deal_version": 1
    },
    "6813b6d546e731854c7ac855": {
      "name": "Ecuador",
      "code": "ec",
      "rate": 6.0,
      "factories": 7,
      "workers": 7,
      "irish_workers": 2,
      "foreign_workers": 5,
      "wages": 509.13,
      "tax": 30.55,
      "irish_worker_tax": 0.95,
      "foreign_worker_tax": 29.6,
      "manual_rebate_due": 0.0,
      "host_retained": 21.39,
      "irish_rebate": 0,
      "foreign_rebate": 0,
      "deal_version": 1
    },
    "6873d0ea1758b40e712b5ef5": {
      "name": "Cameroon",
      "code": "cm",
      "rate": 5.0,
      "factories": 15,
      "workers": 15,
      "irish_workers": 9,
      "foreign_workers": 6,
      "wages": 430.72,
      "tax": 44.02,
      "irish_worker_tax": 23.88,
      "foreign_worker_tax": 20.14,
      "manual_rebate_due": 0.0,
      "host_retained": 30.81,
      "irish_rebate": 0,
      "foreign_rebate": 0,
      "deal_version": 1
    },
    "6813b6d546e731854c7ac890": {
      "name": "Greenland",
      "code": "gl",
      "rate": 10.0,
      "factories": 5,
      "workers": 6,
      "irish_workers": 0,
      "foreign_workers": 6,
      "wages": 208.5,
      "tax": 20.85,
      "irish_worker_tax": 0.0,
      "foreign_worker_tax": 20.85,
      "manual_rebate_due": 0.0,
      "host_retained": 14.6,
      "irish_rebate": 0,
      "foreign_rebate": 0,
      "deal_version": 1
    },
    "6813b6d446e731854c7ac7f8": {
      "name": "Mexico",
      "code": "mx",
      "rate": 4.0,
      "factories": 6,
      "workers": 9,
      "irish_workers": 0,
      "foreign_workers": 9,
      "wages": 490.73,
      "tax": 19.63,
      "irish_worker_tax": 0.0,
      "foreign_worker_tax": 19.63,
      "manual_rebate_due": 0.0,
      "host_retained": 13.74,
      "irish_rebate": 0,
      "foreign_rebate": 0,
      "deal_version": 1
    },
    "6813b6d446e731854c7ac7c0": {
      "name": "Latvia",
      "code": "lv",
      "rate": 7.0,
      "factories": 9,
      "workers": 9,
      "irish_workers": 6,
      "foreign_workers": 3,
      "wages": 345.12,
      "tax": 24.16,
      "irish_worker_tax": 3.39,
      "foreign_worker_tax": 20.77,
      "manual_rebate_due": 0.0,
      "host_retained": 16.91,
      "irish_rebate": 0,
      "foreign_rebate": 0,
      "deal_version": 1
    },
    "683ddd2c24b5a2e114af1603": {
      "name": "Somalia",
      "code": "so",
      "rate": 5.0,
      "factories": 2,
      "workers": 2,
      "irish_workers": 2,
      "foreign_workers": 0,
      "wages": 163.46,
      "tax": 8.17,
      "irish_worker_tax": 8.17,
      "foreign_worker_tax": 0.0,
      "manual_rebate_due": 0.0,
      "host_retained": 5.72,
      "irish_rebate": 0,
      "foreign_rebate": 0,
      "deal_version": 1
    },
    "683ddd2c24b5a2e114af15d9": {
      "name": "Malaysia",
      "code": "my",
      "rate": 3.0,
      "factories": 7,
      "workers": 9,
      "irish_workers": 3,
      "foreign_workers": 6,
      "wages": 463.2,
      "tax": 13.89,
      "irish_worker_tax": 8.17,
      "foreign_worker_tax": 5.72,
      "manual_rebate_due": 0.0,
      "host_retained": 9.72,
      "irish_rebate": 0,
      "foreign_rebate": 0,
      "deal_version": 1
    },
    "6813b6d546e731854c7ac8b2": {
      "name": "El Salvador",
      "code": "sv",
      "rate": 3.0,
      "factories": 6,
      "workers": 6,
      "irish_workers": 0,
      "foreign_workers": 6,
      "wages": 442.32,
      "tax": 13.27,
      "irish_worker_tax": 0.0,
      "foreign_worker_tax": 13.27,
      "manual_rebate_due": 0.0,
      "host_retained": 9.29,
      "irish_rebate": 0,
      "foreign_rebate": 0,
      "deal_version": 1
    },
    "6813b6d446e731854c7ac7b8": {
      "name": "Lithuania",
      "code": "lt",
      "rate": 7.0,
      "factories": 3,
      "workers": 3,
      "irish_workers": 3,
      "foreign_workers": 0,
      "wages": 143.73,
      "tax": 10.05,
      "irish_worker_tax": 10.05,
      "foreign_worker_tax": 0.0,
      "manual_rebate_due": 0.0,
      "host_retained": 7.05,
      "irish_rebate": 0,
      "foreign_rebate": 0,
      "deal_version": 1
    },
    "6813b6d546e731854c7ac820": {
      "name": "China",
      "code": "cn",
      "rate": 5.0,
      "factories": 4,
      "workers": 6,
      "irish_workers": 2,
      "foreign_workers": 4,
      "wages": 82.47,
      "tax": 4.12,
      "irish_worker_tax": 4.12,
      "foreign_worker_tax": 0.0,
      "manual_rebate_due": 0.0,
      "host_retained": 2.89,
      "irish_rebate": 0,
      "foreign_rebate": 0,
      "deal_version": 1
    },
    "6813b6d446e731854c7ac7a8": {
      "name": "Spain",
      "code": "es",
      "rate": 4.0,
      "factories": 6,
      "workers": 6,
      "irish_workers": 3,
      "foreign_workers": 3,
      "wages": 359.37,
      "tax": 14.37,
      "irish_worker_tax": 4.84,
      "foreign_worker_tax": 9.53,
      "manual_rebate_due": 0.0,
      "host_retained": 10.06,
      "irish_rebate": 0,
      "foreign_rebate": 0,
      "deal_version": 1
    },
    "683ddd2c24b5a2e114af15d5": {
      "name": "Myanmar",
      "code": "mm",
      "rate": 5.0,
      "factories": 1,
      "workers": 1,
      "irish_workers": 1,
      "foreign_workers": 0,
      "wages": 74.2,
      "tax": 3.71,
      "irish_worker_tax": 3.71,
      "foreign_worker_tax": 0.0,
      "manual_rebate_due": 0.0,
      "host_retained": 2.6,
      "irish_rebate": 0,
      "foreign_rebate": 0,
      "deal_version": 1
    },
    "6813b6d446e731854c7ac80b": {
      "name": "Finland",
      "code": "fi",
      "rate": 7.0,
      "factories": 5,
      "workers": 5,
      "irish_workers": 0,
      "foreign_workers": 5,
      "wages": 373.6,
      "tax": 26.16,
      "irish_worker_tax": 0.0,
      "foreign_worker_tax": 26.16,
      "manual_rebate_due": 0.0,
      "host_retained": 18.31,
      "irish_rebate": 0,
      "foreign_rebate": 0,
      "deal_version": 1
    },
    "683ddd2c24b5a2e114af1606": {
      "name": "Syria",
      "code": "sy",
      "rate": 3.0,
      "factories": 3,
      "workers": 9,
      "irish_workers": 0,
      "foreign_workers": 9,
      "wages": 237.74,
      "tax": 7.13,
      "irish_worker_tax": 0.0,
      "foreign_worker_tax": 7.13,
      "manual_rebate_due": 0.0,
      "host_retained": 4.99,
      "irish_rebate": 0,
      "foreign_rebate": 0,
      "deal_version": 1
    },
    "6813b6d446e731854c7ac7a2": {
      "name": "Italy",
      "code": "it",
      "rate": 7.9,
      "factories": 2,
      "workers": 2,
      "irish_workers": 0,
      "foreign_workers": 2,
      "wages": 52.5,
      "tax": 4.15,
      "irish_worker_tax": 0.0,
      "foreign_worker_tax": 4.15,
      "manual_rebate_due": 0.0,
      "host_retained": 2.9,
      "irish_rebate": 0,
      "foreign_rebate": 0,
      "deal_version": 1
    },
    "696a81da63e2489f47e5a28a": {
      "name": "Comoros",
      "code": "km",
      "rate": 4.0,
      "factories": 2,
      "workers": 2,
      "irish_workers": 2,
      "foreign_workers": 0,
      "wages": 132.39,
      "tax": 5.3,
      "irish_worker_tax": 5.3,
      "foreign_worker_tax": 0.0,
      "manual_rebate_due": 0.0,
      "host_retained": 3.71,
      "irish_rebate": 0,
      "foreign_rebate": 0,
      "deal_version": 1
    },
    "6813b6d546e731854c7ac880": {
      "name": "New Zealand",
      "code": "nz",
      "rate": 3.9,
      "factories": 3,
      "workers": 3,
      "irish_workers": 3,
      "foreign_workers": 0,
      "wages": 163.45,
      "tax": 6.37,
      "irish_worker_tax": 6.37,
      "foreign_worker_tax": 0.0,
      "manual_rebate_due": 0.0,
      "host_retained": 4.46,
      "irish_rebate": 0,
      "foreign_rebate": 0,
      "deal_version": 1
    },
    "683ddd2c24b5a2e114af15c5": {
      "name": "Iceland",
      "code": "is",
      "rate": 10.0,
      "factories": 4,
      "workers": 5,
      "irish_workers": 3,
      "foreign_workers": 2,
      "wages": 210.87,
      "tax": 21.09,
      "irish_worker_tax": 16.27,
      "foreign_worker_tax": 4.82,
      "manual_rebate_due": 0.0,
      "host_retained": 14.76,
      "irish_rebate": 0,
      "foreign_rebate": 0,
      "deal_version": 1
    },
    "6813b6d446e731854c7ac808": {
      "name": "Canada",
      "code": "ca",
      "rate": 6.0,
      "factories": 2,
      "workers": 4,
      "irish_workers": 1,
      "foreign_workers": 3,
      "wages": 105.06,
      "tax": 6.31,
      "irish_worker_tax": 0.9,
      "foreign_worker_tax": 5.41,
      "manual_rebate_due": 0.0,
      "host_retained": 4.41,
      "irish_rebate": 0,
      "foreign_rebate": 0,
      "deal_version": 1
    },
    "6813b6d446e731854c7ac7fe": {
      "name": "Ireland",
      "code": "ie",
      "rate": 4.0,
      "factories": 3,
      "workers": 12,
      "irish_workers": 4,
      "foreign_workers": 8,
      "wages": 119.21,
      "tax": 4.76,
      "irish_worker_tax": 1.26,
      "foreign_worker_tax": 3.51,
      "manual_rebate_due": 0.0,
      "host_retained": 3.34,
      "irish_rebate": 0,
      "foreign_rebate": 0,
      "deal_version": 1
    },
    "6813b6d546e731854c7ac8af": {
      "name": "Nicaragua",
      "code": "ni",
      "rate": 4.0,
      "factories": 6,
      "workers": 12,
      "irish_workers": 0,
      "foreign_workers": 12,
      "wages": 62.42,
      "tax": 2.26,
      "irish_worker_tax": 0.0,
      "foreign_worker_tax": 2.26,
      "manual_rebate_due": 0.0,
      "host_retained": 1.57,
      "irish_rebate": 0,
      "foreign_rebate": 0,
      "deal_version": 1
    },
    "6813b6d546e731854c7ac842": {
      "name": "Cyprus",
      "code": "cy",
      "rate": 6.0,
      "factories": 5,
      "workers": 5,
      "irish_workers": 0,
      "foreign_workers": 5,
      "wages": 23.75,
      "tax": 1.43,
      "irish_worker_tax": 0.0,
      "foreign_worker_tax": 1.43,
      "manual_rebate_due": 0.0,
      "host_retained": 1.0,
      "irish_rebate": 0,
      "foreign_rebate": 0,
      "deal_version": 1
    },
    "6813b6d546e731854c7ac865": {
      "name": "Ukraine",
      "code": "ua",
      "rate": 10.0,
      "factories": 2,
      "workers": 2,
      "irish_workers": 2,
      "foreign_workers": 0,
      "wages": 11.55,
      "tax": 1.16,
      "irish_worker_tax": 1.16,
      "foreign_worker_tax": 0.0,
      "manual_rebate_due": 0.0,
      "host_retained": 0.81,
      "irish_rebate": 0,
      "foreign_rebate": 0,
      "deal_version": 1
    },
    "6813b6d546e731854c7ac871": {
      "name": "Singapore",
      "code": "sg",
      "rate": 5.0,
      "factories": 3,
      "workers": 3,
      "irish_workers": 3,
      "foreign_workers": 0,
      "wages": 27.3,
      "tax": 1.36,
      "irish_worker_tax": 1.36,
      "foreign_worker_tax": 0.0,
      "manual_rebate_due": 0.0,
      "host_retained": 0.96,
      "irish_rebate": 0,
      "foreign_rebate": 0,
      "deal_version": 1
    },
    "683ddd2c24b5a2e114af15bf": {
      "name": "Georgia",
      "code": "ge",
      "rate": 3.0,
      "factories": 4,
      "workers": 4,
      "irish_workers": 3,
      "foreign_workers": 1,
      "wages": 125.15,
      "tax": 3.75,
      "irish_worker_tax": 0.7,
      "foreign_worker_tax": 3.05,
      "manual_rebate_due": 0.0,
      "host_retained": 2.64,
      "irish_rebate": 0,
      "foreign_rebate": 0,
      "deal_version": 1
    },
    "6813b6d446e731854c7ac7a4": {
      "name": "Belgium",
      "code": "be",
      "rate": 10.0,
      "factories": 3,
      "workers": 3,
      "irish_workers": 0,
      "foreign_workers": 3,
      "wages": 0.0,
      "tax": 0.0,
      "irish_worker_tax": 0.0,
      "foreign_worker_tax": 0.0,
      "manual_rebate_due": 0.0,
      "host_retained": 0.0,
      "irish_rebate": 0,
      "foreign_rebate": 0,
      "deal_version": 1
    },
    "6873d0ea1758b40e712b5f73": {
      "name": "Zambia",
      "code": "zm",
      "rate": 4.0,
      "factories": 3,
      "workers": 3,
      "irish_workers": 0,
      "foreign_workers": 3,
      "wages": 0.0,
      "tax": 0.0,
      "irish_worker_tax": 0.0,
      "foreign_worker_tax": 0.0,
      "manual_rebate_due": 0.0,
      "host_retained": 0.0,
      "irish_rebate": 0,
      "foreign_rebate": 0,
      "deal_version": 1
    },
    "6813b6d546e731854c7ac8b5": {
      "name": "Honduras",
      "code": "hn",
      "rate": 4.0,
      "factories": 3,
      "workers": 3,
      "irish_workers": 0,
      "foreign_workers": 3,
      "wages": 191.13,
      "tax": 7.64,
      "irish_worker_tax": 0.0,
      "foreign_worker_tax": 7.64,
      "manual_rebate_due": 0.0,
      "host_retained": 5.35,
      "irish_rebate": 0,
      "foreign_rebate": 0,
      "deal_version": 1
    },
    "6873d0ea1758b40e712b5f37": {
      "name": "Burkina Faso",
      "code": "bf",
      "rate": 7.0,
      "factories": 4,
      "workers": 8,
      "irish_workers": 0,
      "foreign_workers": 8,
      "wages": 45.02,
      "tax": 1.31,
      "irish_worker_tax": 0.0,
      "foreign_worker_tax": 1.31,
      "manual_rebate_due": 0.0,
      "host_retained": 0.91,
      "irish_rebate": 0,
      "foreign_rebate": 0,
      "deal_version": 1
    },
    "6813b6d546e731854c7ac86e": {
      "name": "Kenya",
      "code": "ke",
      "rate": 9.0,
      "factories": 1,
      "workers": 1,
      "irish_workers": 0,
      "foreign_workers": 1,
      "wages": 13.77,
      "tax": 1.24,
      "irish_worker_tax": 0.0,
      "foreign_worker_tax": 1.24,
      "manual_rebate_due": 0.0,
      "host_retained": 0.87,
      "irish_rebate": 0,
      "foreign_rebate": 0,
      "deal_version": 1
    },
    "683ddd2c24b5a2e114af1609": {
      "name": "Thailand",
      "code": "th",
      "rate": 1.0,
      "factories": 1,
      "workers": 2,
      "irish_workers": 0,
      "foreign_workers": 2,
      "wages": 0.0,
      "tax": 0.0,
      "irish_worker_tax": 0.0,
      "foreign_worker_tax": 0.0,
      "manual_rebate_due": 0.0,
      "host_retained": 0.0,
      "irish_rebate": 0,
      "foreign_rebate": 0,
      "deal_version": 1
    }
  }
}