{"userId":"6a3018b4d22a6bcec74e9d2a","username":"Kianthek","snapshots":[{"t":"2026-06-15T23:22:02.044727+00:00","total":312.43,"companies":79.16,"items":215.33,"money":8.34,"equipments":4.09,"weapons":5.5},{"t":"2026-06-16T23:07:42.560360+00:00","total":437.64,"companies":111.53,"items":204.29,"money":106.62,"equipments":11.87,"weapons":3.33},{"t":"2026-06-17T23:08:40.340275+00:00","total":513.27,"companies":270.14,"items":177.15,"money":55.94,"equipments":7.37,"weapons":2.68},{"t":"2026-06-18T23:22:09.895649+00:00","total":590.11,"companies":270.5,"items":155.22,"money":124.12,"equipments":30.79,"weapons":9.48},{"t":"2026-06-19T22:32:58.250380+00:00","total":628.74,"companies":285.35,"items":160.56,"money":107.87,"equipments":47.66,"weapons":27.29},{"t":"2026-06-20T22:46:25.114057+00:00","total":690.57,"companies":316.2,"items":244.1,"money":50.76,"equipments":52.51,"weapons":26.99},{"t":"2026-06-21T02:01:07.488135+00:00","total":687.87,"companies":315.12,"items":242.81,"money":50.76,"equipments":52.31,"weapons":26.87},{"t":"2026-06-23T10:45:44.459883+00:00","total":813.11,"companies":316.33,"items":424.95,"money":1.93,"equipments":45.08,"weapons":24.83}]}