{"userId":"6a39ab3f073032b03f3af959","username":"LenDeLaMuerte","snapshots":[{"t":"2026-06-23T11:42:14.017397+00:00","total":303.62,"companies":79.12,"items":211.51,"money":3.49,"equipments":8.0,"weapons":1.49},{"t":"2026-06-24T10:36:10.290867+00:00","total":304.62,"companies":79.56,"items":212.13,"money":3.49,"equipments":7.95,"weapons":1.5},{"t":"2026-06-25T10:29:00.624185+00:00","total":303.38,"companies":78.89,"items":211.53,"money":3.49,"equipments":7.96,"weapons":1.5},{"t":"2026-06-27T09:17:31.926878+00:00","total":430.18,"companies":80.8,"items":232.86,"money":107.04,"equipments":8.0,"weapons":1.48},{"t":"2026-06-28T08:35:26.441488+00:00","total":438.01,"companies":80.87,"items":237.05,"money":110.59,"equipments":8.02,"weapons":1.48}]}